slack_logger/__init__.py
slack_logger/message_logger.py
slack_logger/utils.py
better_slack_logger-0.12.0.post2.dist-info/LICENSE
better_slack_logger-0.12.0.post2.dist-info/METADATA
better_slack_logger-0.12.0.post2.dist-info/WHEEL
better_slack_logger-0.12.0.post2.dist-info/RECORD
