Metadata-Version: 2.1
Name: better-slack-logger
Version: 0.12.0.post2
Summary: Slack Logger is a custom message logger to Slack for Python 3
Home-page: https://github.com/Kayenta/better-slack-logger
License: MIT
Keywords: monitoring,slack,messaging,logging,health-check,notification-service,notification,slack-api
Author: Chinni Chaitanya
Author-email: chchaitanya95@gmail.com
Maintainer: Jay Turner
Maintainer-email: jay.turner@kayenta.io
Requires-Python: >=3.7
Classifier: Environment :: Web Environment
Classifier: Intended Audience :: Developers
Classifier: License :: OSI Approved :: MIT License
Classifier: Operating System :: OS Independent
Classifier: Programming Language :: Python :: 3
Classifier: Programming Language :: Python :: 3.7
Classifier: Programming Language :: Python :: 3.8
Classifier: Programming Language :: Python :: 3.9
Classifier: Programming Language :: Python :: 3.10
Classifier: Programming Language :: Python :: 3.11
Classifier: Topic :: Internet :: WWW/HTTP
Classifier: Topic :: Internet :: WWW/HTTP :: Dynamic Content
Requires-Dist: pyyaml (>=5.1)
Requires-Dist: slack-sdk (>=3.0.0)
Project-URL: Repository, https://github.com/Kayenta/better-slack-logger
